insilicho/__init__.py
insilicho/chemistry.py
insilicho/growth_model.py
insilicho/parameters.py
insilicho/plotter.py
insilicho/reactor.py
insilicho/run.py
insilicho/solver.py
insilicho/units.py
insilicho/util.py
insilicho-1.1.4.dist-info/LICENSE.md
insilicho-1.1.4.dist-info/WHEEL
insilicho-1.1.4.dist-info/METADATA
insilicho-1.1.4.dist-info/RECORD
