Metadata-Version: 2.1
Name: insilicho
Version: 1.1.4
Summary: An insilico model for CHO cells
License: MIT
Author: Culture Biosciences
Author-email: matt@culturebiosciences.com
Requires-Python: >=3.10,<4.0
Classifier: License :: OSI Approved :: MIT License
Classifier: Programming Language :: Python :: 3
Classifier: Programming Language :: Python :: 3.10
Requires-Dist: Pint (>=0.19.2,<0.20.0)
Requires-Dist: PyYAML (>=6.0,<7.0)
Requires-Dist: mypy (>=0.991,<0.992)
Requires-Dist: numpy (==1.23.5)
Requires-Dist: pandas (>=1.5.0,<2.0.0)
Requires-Dist: scipy (>1.7.0)
